odoo/addons/hr_employee_calendar_planning/README.rst
odoo/addons/hr_employee_calendar_planning/__init__.py
odoo/addons/hr_employee_calendar_planning/__manifest__.py
odoo/addons/hr_employee_calendar_planning/hooks.py
odoo/addons/hr_employee_calendar_planning/i18n/ca.po
odoo/addons/hr_employee_calendar_planning/i18n/ca_ES.po
odoo/addons/hr_employee_calendar_planning/i18n/de.po
odoo/addons/hr_employee_calendar_planning/i18n/es.po
odoo/addons/hr_employee_calendar_planning/i18n/es_AR.po
odoo/addons/hr_employee_calendar_planning/i18n/fr.po
odoo/addons/hr_employee_calendar_planning/i18n/hr_employee_calendar_planning.pot
odoo/addons/hr_employee_calendar_planning/i18n/it.po
odoo/addons/hr_employee_calendar_planning/models/__init__.py
odoo/addons/hr_employee_calendar_planning/models/hr_employee.py
odoo/addons/hr_employee_calendar_planning/models/resource_calendar.py
odoo/addons/hr_employee_calendar_planning/readme/CONFIGURE.md
odoo/addons/hr_employee_calendar_planning/readme/CONTRIBUTORS.md
odoo/addons/hr_employee_calendar_planning/readme/DESCRIPTION.md
odoo/addons/hr_employee_calendar_planning/readme/INSTALL.md
odoo/addons/hr_employee_calendar_planning/readme/ROADMAP.md
odoo/addons/hr_employee_calendar_planning/security/ir.model.access.csv
odoo/addons/hr_employee_calendar_planning/static/description/icon.png
odoo/addons/hr_employee_calendar_planning/static/description/index.html
odoo/addons/hr_employee_calendar_planning/tests/__init__.py
odoo/addons/hr_employee_calendar_planning/tests/test_hr_employee_calendar_planning.py
odoo/addons/hr_employee_calendar_planning/views/hr_employee_views.xml
odoo/addons/hr_employee_calendar_planning/views/resource_calendar_views.xml
odoo_addon_hr_employee_calendar_planning-18.0.1.0.1.dist-info/METADATA
odoo_addon_hr_employee_calendar_planning-18.0.1.0.1.dist-info/WHEEL
odoo_addon_hr_employee_calendar_planning-18.0.1.0.1.dist-info/top_level.txt
odoo_addon_hr_employee_calendar_planning-18.0.1.0.1.dist-info/RECORD
